cycy/__init__.py
cycy/__main__.py
cycy/bytecode.py
cycy/cli.py
cycy/compiler.py
cycy/environment.py
cycy/exceptions.py
cycy/interpreter.py
cycy/objects.py
cycy/repl.py
cycy/target.py
cycy/parser/__init__.py
cycy/parser/ast.py
cycy/parser/lexer.py
cycy/parser/preprocessor.py
cycy/parser/sourceparser.py
cycy/tests/__init__.py
cycy/tests/test_ast.py
cycy/tests/test_cli.py
cycy/tests/test_compiler.py
cycy/tests/test_example.py
cycy/tests/test_interpreter.py
cycy/tests/test_parser.py
cycy/tests/test_preprocessor.py
cycy/tests/test_repl.py
cycy-0.1.post29.data/scripts/cycy
cycy-0.1.post29.dist-info/DESCRIPTION.rst
cycy-0.1.post29.dist-info/entry_points.txt
cycy-0.1.post29.dist-info/METADATA
cycy-0.1.post29.dist-info/pbr.json
cycy-0.1.post29.dist-info/pydist.json
cycy-0.1.post29.dist-info/RECORD
cycy-0.1.post29.dist-info/top_level.txt
cycy-0.1.post29.dist-info/WHEEL
