Metadata-Version: 2.0
Name: cycy
Version: 0.1.post29
Summary: A C interpreter written in RPython
Home-page: https://github.com/Magnetic/CyCy
Author: Julian Berman
Author-email: Julian@GrayVines.com
License: MIT
Platform: UNKNOWN
Classifier: Development Status :: 3 - Alpha
Classifier: License :: OSI Approved :: MIT License
Classifier: Operating System :: OS Independent
Classifier: Programming Language :: Python
Classifier: Programming Language :: Python :: 2.7
Classifier: Programming Language :: Python :: 2
Classifier: Programming Language :: Python :: Implementation :: CPython
Classifier: Programming Language :: Python :: Implementation :: PyPy
Requires-Dist: characteristic (>=14.3.0)
Requires-Dist: rply
Requires-Dist: rpython
